gitlogviz/__init__.py
gitlogviz/gitlogviz.py
gitlogviz-0.1.dist-info/LICENSE
gitlogviz-0.1.dist-info/METADATA
gitlogviz-0.1.dist-info/WHEEL
gitlogviz-0.1.dist-info/entry_points.txt
gitlogviz-0.1.dist-info/top_level.txt
gitlogviz-0.1.dist-info/RECORD
