Metadata-Version: 2.1
Name: gitlogviz
Version: 0.1
Summary: A tool for visualizing Git log in a graph
Home-page: https://github.com/okpyjs/gitlogviz
Author: Oleksandr Koniaiev
Author-email: oleksandrko448@gmail.com
License: MIT
Classifier: License :: OSI Approved :: MIT License
Classifier: Programming Language :: Python :: 3
Classifier: Programming Language :: Python :: 3.6
Classifier: Programming Language :: Python :: 3.7
Classifier: Programming Language :: Python :: 3.8
Classifier: Programming Language :: Python :: 3.9
Classifier: Programming Language :: Python :: 3.10
Classifier: Programming Language :: Python :: 3.11
Requires-Python: >=3.6
License-File: LICENSE
Requires-Dist: matplotlib
